cameo/__init__.py
cameo/_version.py
cameo/config.py
cameo/exceptions.py
cameo/io.py
cameo/parallel.py
cameo/util.py
cameo/api/__init__.py
cameo/api/designer.py
cameo/api/hosts.py
cameo/api/products.py
cameo/core/__init__.py
cameo/core/manipulation.py
cameo/core/model_dual.py
cameo/core/pathway.py
cameo/core/result.py
cameo/core/strain_design.py
cameo/core/target.py
cameo/core/utils.py
cameo/data/__init__.py
cameo/data/metanetx.json.gz
cameo/data/metanetx.py
cameo/data/metanetx_chem_prop.json.gz
cameo/flux_analysis/__init__.py
cameo/flux_analysis/analysis.py
cameo/flux_analysis/simulation.py
cameo/flux_analysis/structural.py
cameo/flux_analysis/util.py
cameo/models/__init__.py
cameo/models/universal.py
cameo/models/webmodels.py
cameo/models/json/e_coli_core.json
cameo/models/json/iJO1366.json
cameo/models/json/iMM904.json
cameo/models/sbml/iJO1366.xml
cameo/models/sbml/iMM904.xml
cameo/models/sbml/legacy_sbml/iJO1366.xml
cameo/models/sbml/legacy_sbml/iMM904.xml
cameo/models/universal_models/metanetx_universal_model_bigg.json
cameo/models/universal_models/metanetx_universal_model_bigg_rhea.json
cameo/models/universal_models/metanetx_universal_model_bigg_rhea_kegg.json
cameo/models/universal_models/metanetx_universal_model_bigg_rhea_kegg_brenda.json
cameo/models/universal_models/metanetx_universal_model_rhea.json
cameo/network_analysis/__init__.py
cameo/network_analysis/networkx_based.py
cameo/network_analysis/util.py
cameo/strain_design/__init__.py
cameo/strain_design/deterministic/__init__.py
cameo/strain_design/deterministic/flux_variability_based.py
cameo/strain_design/deterministic/linear_programming.py
cameo/strain_design/heuristic/__init__.py
cameo/strain_design/heuristic/evolutionary_based.py
cameo/strain_design/heuristic/evolutionary/__init__.py
cameo/strain_design/heuristic/evolutionary/archives.py
cameo/strain_design/heuristic/evolutionary/decoders.py
cameo/strain_design/heuristic/evolutionary/evaluators.py
cameo-0.13.6.dist-info/LICENSE
cameo-0.13.6.dist-info/METADATA
cameo-0.13.6.dist-info/WHEEL
cameo-0.13.6.dist-info/entry_points.txt
cameo-0.13.6.dist-info/top_level.txt
cameo-0.13.6.dist-info/RECORD
