Metadata-Version: 2.1
Name: cameo
Version: 0.13.6
Summary: cameo - computer aided metabolic engineering & optimization
Home-page: http://cameo.bio
Author: Nikolaus Sonnenschein, Joao Cardoso, Emre Özdemir, Kristian Jensen
Author-email: niko.sonnenschein@gmail.com
License: Apache License Version 2.0
Keywords: biology metabolism bioinformatics
Platform: UNKNOWN
Classifier: Development Status :: 3 - Alpha
Classifier: Topic :: Utilities
Classifier: Programming Language :: Python :: 3.6
Classifier: Programming Language :: Python :: 3.7
Classifier: Programming Language :: Python :: 3.8
Classifier: License :: OSI Approved :: Apache Software License
Provides-Extra: docs
Provides-Extra: plotly
Provides-Extra: bokeh
Provides-Extra: jupyter
Provides-Extra: test
Provides-Extra: parallel
Provides-Extra: sbml
Provides-Extra: all
License-File: LICENSE
